llmppl/__init__.py
llmppl/core.py
llmppl/gpt35.py
llmppl/llama2.py
llmppl/mamba.py
llmppl/mistral.py
llmppl/rwkv.py
llmppl-0.1.3.dist-info/LICENSE
llmppl-0.1.3.dist-info/METADATA
llmppl-0.1.3.dist-info/WHEEL
llmppl-0.1.3.dist-info/top_level.txt
llmppl-0.1.3.dist-info/RECORD
