Metadata-Version: 2.1
Name: llmppl
Version: 0.1.3
Summary: A package for calculating perplexity using various language models
Home-page: https://github.com/Arrtourz/llmppl
Author: Zhenyu Xu
Author-email: thornscrown1220@gmail.com
Classifier: Programming Language :: Python :: 3
Classifier: License :: OSI Approved :: MIT License
Classifier: Operating System :: OS Independent
Requires-Python: >=3.9
License-File: LICENSE
Requires-Dist: transformers==4.45.2
Requires-Dist: openai==0.28.0
Requires-Dist: tqdm==4.66.5
Requires-Dist: sentencepiece==0.2.0
Requires-Dist: bitsandbytes==0.44.1
Requires-Dist: accelerate==1.0.1
Requires-Dist: protobuf==5.28.2
Requires-Dist: tiktoken==0.8.0
